[
  {
    "code": "JO-AJ",
    "name": "‘Ajlūn",
    "category": null
  },
  {
    "code": "JO-AQ",
    "name": "Al ‘Aqabah",
    "category": null
  },
  {
    "code": "JO-AM",
    "name": "Al ‘A̅şimah",
    "category": null
  },
  {
    "code": "JO-BA",
    "name": "Al Balqā’",
    "category": null
  },
  {
    "code": "JO-KA",
    "name": "Al Karak",
    "category": null
  },
  {
    "code": "JO-MA",
    "name": "Al Mafraq",
    "category": null
  },
  {
    "code": "JO-AT",
    "name": "Aţ Ţafīlah",
    "category": null
  },
  {
    "code": "JO-AZ",
    "name": "Az Zarqā’",
    "category": null
  },
  {
    "code": "JO-IR",
    "name": "Irbid",
    "category": null
  },
  {
    "code": "JO-JA",
    "name": "Jarash",
    "category": null
  },
  {
    "code": "JO-MN",
    "name": "Ma‘ān",
    "category": null
  },
  {
    "code": "JO-MD",
    "name": "Mādabā",
    "category": null
  }
]